dragondrop/__init__.py
dragondrop-0.0.0.0.dist-info/LICENSE
dragondrop-0.0.0.0.dist-info/METADATA
dragondrop-0.0.0.0.dist-info/WHEEL
dragondrop-0.0.0.0.dist-info/top_level.txt
dragondrop-0.0.0.0.dist-info/RECORD
